{
    "pools": [
        {
            "rolls": 1,
            "entries": [
                {
                    "type": "minecraft:item",
                    "name": "minecraft:arrow",
                    "functions": [
                        {
                            "function": "set_nbt",
                            "tag": "{origami-games:{launch:{item:\"custom_arrow\",arrow:\"torch\"}},display:{Name:'{\"translate\":\"item.launch.torch_arrow\",\"italic\":false}'},CustomModelData:7510004}"
                        }
                    ]
                }
            ]
        }
    ]
}
